{"['est', 'int\u00e9ress\u00e9e', 'de']": "int\u00e9ress\u00e9e", "['presque', '\u00e0']": "\u00e0", "['nous', 'd\u00e9butons']": "d\u00e9butons", "['pallier', 'au']": "pallier", "['tout', 'de', 'suite']": "suite", "['seraient', 'int\u00e9ress\u00e9s', 'de']": "int\u00e9ress\u00e9s", "['\u00c0', 'l'', 'instar', 'de']": "instar", "['seraient', 'int\u00e9ress\u00e9s', \"d'\"]": "int\u00e9ress\u00e9s", "['\u00e9taient', 'int\u00e9ress\u00e9s']": "int\u00e9ress\u00e9s", "['\u00bb', '(', 'Voltaire<', ')']": "(", "['a', 'été']": "été"}